kreatornow/__init__.py
kreatornow/kreatornow.py
kreatornow/utils.py
kreatornow-1.0.1.dist-info/LICENSE
kreatornow-1.0.1.dist-info/METADATA
kreatornow-1.0.1.dist-info/WHEEL
kreatornow-1.0.1.dist-info/top_level.txt
kreatornow-1.0.1.dist-info/RECORD
